{
  "firstLayout": "",
  "gdVersion": {
    "build": 98,
    "major": 4,
    "minor": 0,
    "revision": 0
  },
  "properties": {
    "adMobAppId": "",
    "folderProject": false,
    "linuxExecutableFilename": "",
    "macExecutableFilename": "",
    "orientation": "landscape",
    "packageName": "com.example.gamename",
    "projectFile": "C:\\Users\\Lennart\\Documents\\DoubleShoot\\DoubleShoot\\doubleshoot.json",
    "scaleMode": "linear",
    "sizeOnStartupMode": "adaptWidth",
    "useExternalSourceFiles": false,
    "version": "0.0.1",
    "winExecutableFilename": "",
    "winExecutableIconFile": "",
    "name": "DoubleShoot",
    "author": "",
    "windowWidth": 800,
    "windowHeight": 600,
    "latestCompilationDirectory": "",
    "maxFPS": 60,
    "minFPS": 25,
    "verticalSync": false,
    "platformSpecificAssets": {},
    "loadingScreen": {
      "showGDevelopSplash": true
    },
    "extensions": [
      {
        "name": "BuiltinObject"
      },
      {
        "name": "BuiltinAudio"
      },
      {
        "name": "BuiltinVariables"
      },
      {
        "name": "BuiltinTime"
      },
      {
        "name": "BuiltinMouse"
      },
      {
        "name": "BuiltinKeyboard"
      },
      {
        "name": "BuiltinJoystick"
      },
      {
        "name": "BuiltinCamera"
      },
      {
        "name": "BuiltinWindow"
      },
      {
        "name": "BuiltinFile"
      },
      {
        "name": "BuiltinNetwork"
      },
      {
        "name": "BuiltinScene"
      },
      {
        "name": "BuiltinAdvanced"
      },
      {
        "name": "Sprite"
      },
      {
        "name": "BuiltinCommonInstructions"
      },
      {
        "name": "BuiltinCommonConversions"
      },
      {
        "name": "BuiltinStringInstructions"
      },
      {
        "name": "BuiltinMathematicalTools"
      },
      {
        "name": "BuiltinExternalLayouts"
      }
    ],
    "platforms": [
      {
        "name": "GDevelop JS platform"
      }
    ],
    "currentPlatform": "GDevelop JS platform"
  },
  "resources": {
    "resources": [
      {
        "alwaysLoaded": false,
        "file": "laugh1_24055.jpg",
        "kind": "image",
        "metadata": "",
        "name": "laugh1_24055.jpg",
        "smoothed": true,
        "userAdded": true
      }
    ],
    "resourceFolders": []
  },
  "objects": [],
  "objectsGroups": [],
  "variables": [],
  "layouts": [
    {
      "b": 209,
      "disableInputWhenNotFocused": true,
      "mangledName": "NewScene",
      "name": "NewScene",
      "oglFOV": 90,
      "oglZFar": 500,
      "oglZNear": 1,
      "r": 209,
      "standardSortMethod": true,
      "stopSoundsOnStartup": true,
      "title": "",
      "v": 209,
      "uiSettings": {
        "grid": false,
        "gridB": 255,
        "gridG": 180,
        "gridHeight": 32,
        "gridOffsetX": 0,
        "gridOffsetY": 0,
        "gridR": 158,
        "gridWidth": 32,
        "snap": true,
        "windowMask": false,
        "zoomFactor": 1
      },
      "objectsGroups": [],
      "variables": [],
      "instances": [
        {
          "angle": 0,
          "customSize": false,
          "height": 0,
          "layer": "",
          "locked": false,
          "name": "ShootPoint_Left",
          "width": 0,
          "x": 51,
          "y": 277,
          "zOrder": 1,
          "numberProperties": [],
          "stringProperties": [],
          "initialVariables": []
        },
        {
          "angle": 0,
          "customSize": false,
          "height": 0,
          "layer": "",
          "locked": false,
          "name": "ShootPoint_Right",
          "width": 0,
          "x": 209,
          "y": 83,
          "zOrder": 2,
          "numberProperties": [],
          "stringProperties": [],
          "initialVariables": []
        },
        {
          "angle": 0,
          "customSize": false,
          "height": 0,
          "layer": "",
          "locked": false,
          "name": "Text",
          "width": 0,
          "x": 109,
          "y": 37,
          "zOrder": 3,
          "numberProperties": [],
          "stringProperties": [],
          "initialVariables": []
        }
      ],
      "objects": [
        {
          "name": "ShootPoint_Right",
          "tags": "",
          "type": "Sprite",
          "updateIfNotVisible": false,
          "variables": [],
          "behaviors": [
            {
              "name": "Anchor",
              "type": "AnchorBehavior::AnchorBehavior",
              "bottomEdgeAnchor": 0,
              "leftEdgeAnchor": 0,
              "relativeToOriginalWindowSize": true,
              "rightEdgeAnchor": 0,
              "topEdgeAnchor": 0
            }
          ],
          "animations": [
            {
              "name": "",
              "useMultipleDirections": false,
              "directions": [
                {
                  "looping": false,
                  "timeBetweenFrames": 0.08,
                  "sprites": [
                    {
                      "hasCustomCollisionMask": false,
                      "image": "laugh1_24055.jpg",
                      "points": [],
                      "originPoint": {
                        "name": "origine",
                        "x": 0,
                        "y": 0
                      },
                      "centerPoint": {
                        "automatic": true,
                        "name": "centre",
                        "x": 0,
                        "y": 0
                      },
                      "customCollisionMask": []
                    }
                  ]
                }
              ]
            }
          ]
        },
        {
          "name": "ShootPoint_Left",
          "tags": "",
          "type": "Sprite",
          "updateIfNotVisible": false,
          "variables": [],
          "behaviors": [
            {
              "name": "Anchor",
              "type": "AnchorBehavior::AnchorBehavior",
              "bottomEdgeAnchor": 0,
              "leftEdgeAnchor": 0,
              "relativeToOriginalWindowSize": true,
              "rightEdgeAnchor": 0,
              "topEdgeAnchor": 0
            }
          ],
          "animations": []
        },
        {
          "bold": false,
          "italic": false,
          "name": "Text",
          "smoothed": true,
          "tags": "",
          "type": "TextObject::Text",
          "underlined": false,
          "variables": [],
          "behaviors": [],
          "string": "Text",
          "font": "",
          "characterSize": 20,
          "color": {
            "b": 0,
            "g": 0,
            "r": 0
          }
        }
      ],
      "events": [
        {
          "disabled": false,
          "folded": false,
          "type": "BuiltinCommonInstructions::Standard",
          "conditions": [
            {
              "type": {
                "inverted": false,
                "value": "SourisSurObjet"
              },
              "parameters": [
                "ShootPoint_Right",
                "",
                "yes",
                ""
              ],
              "subInstructions": []
            },
            {
              "type": {
                "inverted": false,
                "value": "SourisBouton"
              },
              "parameters": [
                "",
                "Left"
              ],
              "subInstructions": []
            }
          ],
          "actions": [
            {
              "type": {
                "inverted": false,
                "value": "ChangeHeight"
              },
              "parameters": [
                "ShootPoint_Right",
                "=",
                "100\n"
              ],
              "subInstructions": []
            }
          ],
          "events": []
        }
      ],
      "layers": [
        {
          "name": "",
          "visibility": true,
          "cameras": [
            {
              "defaultSize": true,
              "defaultViewport": true,
              "height": 0,
              "viewportBottom": 1,
              "viewportLeft": 0,
              "viewportRight": 1,
              "viewportTop": 0,
              "width": 0
            }
          ],
          "effects": []
        }
      ],
      "behaviorsSharedData": [
        {
          "name": "Anchor",
          "type": "AnchorBehavior::AnchorBehavior"
        }
      ]
    }
  ],
  "externalEvents": [],
  "eventsFunctionsExtensions": [],
  "externalLayouts": [],
  "externalSourceFiles": []
}